ray_ascend/__init__.py
ray_ascend/_version.py
ray_ascend/register.py
ray_ascend-0.1.0.dist-info/licenses/LICENSE
ray_ascend-0.1.0.dist-info/METADATA
ray_ascend-0.1.0.dist-info/WHEEL
ray_ascend-0.1.0.dist-info/top_level.txt
ray_ascend-0.1.0.dist-info/RECORD
