Metadata-Version: 2.4
Name: ray-ascend
Version: 0.1.0
Summary: Community maintained hardware plugin for Ray on Ascend
Author: ray-ascend contributors
Maintainer: ray-ascend contributors
License:                                  Apache License
Project-URL: Homepage, https://github.com/tianyi-ge/ray-ascend
Project-URL: Repository, https://github.com/tianyi-ge/ray-ascend
Project-URL: Issues, https://github.com/tianyi-ge/ray-ascend/issues
Keywords: ray,ascend,distributed computing,machine learning
Classifier: Development Status :: 3 - Alpha
Classifier: Intended Audience :: Developers
Classifier: Intended Audience :: Science/Research
Classifier: License :: OSI Approved :: Apache Software License
Classifier: Operating System :: OS Independent
Classifier: Programming Language :: Python :: 3
Classifier: Programming Language :: Python :: 3.8
Classifier: Programming Language :: Python :: 3.9
Classifier: Programming Language :: Python :: 3.10
Classifier: Programming Language :: Python :: 3.11
Classifier: Programming Language :: Python :: 3.12
Classifier: Topic :: Scientific/Engineering :: Artificial Intelligence
Classifier: Topic :: System :: Distributed Computing
Requires-Python: >=3.8
License-File: LICENSE
Requires-Dist: ray>=2.50.0
Provides-Extra: dev
Requires-Dist: pytest>=7.0.0; extra == "dev"
Requires-Dist: pytest-cov>=4.0.0; extra == "dev"
Requires-Dist: black~=24.1.0; extra == "dev"
Requires-Dist: isort~=5.13.0; extra == "dev"
Requires-Dist: flake8~=7.0.0; extra == "dev"
Requires-Dist: mypy~=1.8.0; extra == "dev"
Requires-Dist: pre-commit>=3.0.0; extra == "dev"
Dynamic: license-file
